allennlp_optuna/__init__.py
allennlp_optuna/commands/__init__.py
allennlp_optuna/commands/best_params.py
allennlp_optuna/commands/retrain.py
allennlp_optuna/commands/tune.py
allennlp_optuna-0.1.7.dist-info/LICENSE
allennlp_optuna-0.1.7.dist-info/WHEEL
allennlp_optuna-0.1.7.dist-info/METADATA
allennlp_optuna-0.1.7.dist-info/RECORD
