Metadata-Version: 2.1
Name: allennlp-optuna
Version: 0.1.7
Summary: AllenNLP integration for hyperparameter optimization
Author: himkt
Author-email: himkt@klis.tsukuba.ac.jp
Requires-Python: >=3.7.1,<4.0.0
Classifier: Programming Language :: Python :: 3
Classifier: Programming Language :: Python :: 3.8
Classifier: Programming Language :: Python :: 3.9
Requires-Dist: allennlp (>=2.6.0,<3.0.0)
Requires-Dist: importlib-metadata (>=4.8.2,<5.0.0)
Requires-Dist: optuna (>=2.6.0,<3.0.0)
